README.rst
setup.cfg
setup.py
./__init__.py
./report_html_stock.py
./report_html_stock.xml
./stock.py
./tryton.cfg
./reports/base.html
./reports/consolidated_picking_list.html
./reports/customer_restocking_list.html
./reports/delivery_note.html
./reports/internal_shipment.html
./reports/picking_list.html
./reports/product_ledger.html
./reports/restocking_base.html
./reports/supplier_restocking_list.html
./reports/css/bootstrap/css/bootstrap.min.css
./reports/css/bootstrap/fonts/glyphicons-halflings-regular.eot
./reports/css/bootstrap/fonts/glyphicons-halflings-regular.svg
./reports/css/bootstrap/fonts/glyphicons-halflings-regular.ttf
./reports/css/bootstrap/fonts/glyphicons-halflings-regular.woff
./reports/css/bootstrap/fonts/glyphicons-halflings-regular.woff2
./reports/css/font-awesome/css/font-awesome.min.css
./reports/css/font-awesome/fonts/FontAwesome.otf
./reports/css/font-awesome/fonts/fontawesome-webfont.eot
./reports/css/font-awesome/fonts/fontawesome-webfont.svg
./reports/css/font-awesome/fonts/fontawesome-webfont.ttf
./reports/css/font-awesome/fonts/fontawesome-webfont.woff
./reports/css/font-awesome/fonts/fontawesome-webfont.woff2
./reports/js/jquery-1.3.2.min.js
./reports/js/jquery-barcode.min.js
./tests/__init__.py
./tests/test_base.py
./tests/test_shipment.py
./view/product_ledger_view_form.xml
fio_report_html_stock.egg-info/PKG-INFO
fio_report_html_stock.egg-info/SOURCES.txt
fio_report_html_stock.egg-info/dependency_links.txt
fio_report_html_stock.egg-info/entry_points.txt
fio_report_html_stock.egg-info/not-zip-safe
fio_report_html_stock.egg-info/requires.txt
fio_report_html_stock.egg-info/top_level.txt